paquete/__init__.py
paquete/courses.py
paquete/utils.py
Test_Cayetano_Rivera_2025-0.0.1.dist-info/METADATA
Test_Cayetano_Rivera_2025-0.0.1.dist-info/WHEEL
Test_Cayetano_Rivera_2025-0.0.1.dist-info/top_level.txt
Test_Cayetano_Rivera_2025-0.0.1.dist-info/RECORD
