Metadata-Version: 2.2
Name: Test_Cayetano_Rivera_2025
Version: 0.0.1
Summary: Una biblioteca para consultar cursos de hack4u.
Home-page: https://pypi.org/
Author: Cayetano Rivera
Dynamic: author
Dynamic: description
Dynamic: description-content-type
Dynamic: home-page
Dynamic: summary
